<?xml version='1.0' encoding='UTF-8'?>
<DEFECTS><DEFECT><SFA><FILEPATH>c:\users\bebo\source\repos\cpp-graphes-2017\cgrpahes\cgrpahes\</FILEPATH><FILENAME>cgraphe.cpp</FILENAME><LINE>147</LINE><COLUMN>37</COLUMN></SFA><DEFECTCODE>6308</DEFECTCODE><DESCRIPTION>'realloc' peut retourner un pointeur Null : l'attribution d'un pointeur Null à 'ppqGRASommets' passé comme argument à 'realloc' peut entraîner une fuite du bloc de mémoire d'origine.</DESCRIPTION><FUNCTION>CGraphe::GRAAjoutSommet</FUNCTION><DECORATED>?GRAAjoutSommet@CGraphe@@QAEXIPAVCArc@@0@Z</DECORATED><FUNCLINE>139</FUNCLINE><PATH/></DEFECT><DEFECT><SFA><FILEPATH>c:\users\bebo\source\repos\cpp-graphes-2017\cgrpahes\cgrpahes\</FILEPATH><FILENAME>cgraphe.cpp</FILENAME><LINE>202</LINE><COLUMN>37</COLUMN></SFA><DEFECTCODE>6308</DEFECTCODE><DESCRIPTION>'realloc' peut retourner un pointeur Null : l'attribution d'un pointeur Null à 'ppqGRASommets' passé comme argument à 'realloc' peut entraîner une fuite du bloc de mémoire d'origine.</DESCRIPTION><FUNCTION>CGraphe::GRASupprimerSommet</FUNCTION><DECORATED>?GRASupprimerSommet@CGraphe@@QAEXPAVCSommet@@@Z</DECORATED><FUNCLINE>182</FUNCLINE><PATH/></DEFECT></DEFECTS>